custom_components/ConversationDesign.py
custom_components/LongTermMemory.py
custom_components/WorkingMemory.py
custom_components/__init__.py
custom_components/_imports_.py
custom_components/antd.css
custom_components/bootstrap-responsive.css
custom_components/bootstrap.css
custom_components/custom.css
custom_components/custom_components.min.js
custom_components/custom_components.min.js.map
custom_components/graph-diagram.css
custom_components/graph-editor.css
custom_components/graph-style-bootstrap.css
custom_components/graph-style-chunky.css
custom_components/metadata.json
custom_components/package-info.json
custom_components/workingmemory.css
custom_components-0.0.1.dist-info/LICENSE
custom_components-0.0.1.dist-info/METADATA
custom_components-0.0.1.dist-info/WHEEL
custom_components-0.0.1.dist-info/top_level.txt
custom_components-0.0.1.dist-info/RECORD
