Metadata-Version: 2.1
Name: custom_components
Version: 0.0.1
Summary: Project Description
Home-page: UNKNOWN
Author: linh.vo <linh@y.digital>
License: MIT
Platform: UNKNOWN
Classifier: Framework :: Dash
License-File: LICENSE
